anyagent/__init__.py
anyagent/base.py
anyagent/schema.py
anyagent/server.py
anyagent/utils.py
anyagent/proto/__init__.py
anyagent/proto/agent.proto
anyagent/proto/agent_pb2.py
anyagent/proto/agent_pb2_grpc.py
anyagent_framework-1.0.0.dist-info/licenses/LICENSE
anyagent_framework-1.0.0.dist-info/METADATA
anyagent_framework-1.0.0.dist-info/WHEEL
anyagent_framework-1.0.0.dist-info/entry_points.txt
anyagent_framework-1.0.0.dist-info/top_level.txt
anyagent_framework-1.0.0.dist-info/RECORD
