Metadata-Version: 2.4
Name: anyagent-framework
Version: 1.0.0
Summary: A standardized framework for building gRPC-based Telegram agents
Home-page: https://github.com/anyagent/anyagent-framework
Author: AnyAgent Team
Author-email: astexlab@gmail.com
Keywords: telegram,agent,grpc,framework,chatbot,ai
Classifier: Development Status :: 4 - Beta
Classifier: Intended Audience :: Developers
Classifier: License :: OSI Approved :: MIT License
Classifier: Programming Language :: Python :: 3
Classifier: Programming Language :: Python :: 3.8
Classifier: Programming Language :: Python :: 3.9
Classifier: Programming Language :: Python :: 3.10
Classifier: Programming Language :: Python :: 3.11
Classifier: Programming Language :: Python :: 3.12
Classifier: Topic :: Software Development :: Libraries :: Python Modules
Classifier: Topic :: Communications :: Chat
Classifier: Topic :: Internet :: WWW/HTTP :: HTTP Servers
Requires-Python: >=3.8
License-File: LICENSE
Requires-Dist: grpcio>=1.68.0
Requires-Dist: grpcio-tools>=1.68.0
Requires-Dist: protobuf>=5.28.2
Requires-Dist: pydantic>=2.10.1
Requires-Dist: aiohttp>=3.11.10
Requires-Dist: requests>=2.31.0
Requires-Dist: chatgpt-md-converter>=0.3.6
Provides-Extra: dev
Requires-Dist: pytest>=7.0.0; extra == "dev"
Requires-Dist: pytest-asyncio>=0.21.0; extra == "dev"
Requires-Dist: black>=23.0.0; extra == "dev"
Requires-Dist: isort>=5.12.0; extra == "dev"
Requires-Dist: mypy>=1.0.0; extra == "dev"
Dynamic: author
Dynamic: author-email
Dynamic: classifier
Dynamic: description
Dynamic: description-content-type
Dynamic: home-page
Dynamic: keywords
Dynamic: license-file
Dynamic: provides-extra
Dynamic: requires-dist
Dynamic: requires-python
Dynamic: summary
